{
	"info": {
		"_postman_id": "c47df35c-c32d-47fb-92d2-408c299db391",
		"name": "SimplesDental",
		"schema": "https://schema.getpostman.com/json/collection/v2.1.0/collection.json",
		"_exporter_id": "30548768"
	},
	"item": [
		{
			"name": "Profissionais",
			"item": [
				{
					"name": "List All",
					"request": {
						"method": "GET",
						"header": [],
						"url": {
							"raw": "localhost:8080/profissionais",
							"host": [
								"localhost"
							],
							"port": "8080",
							"path": [
								"profissionais"
							]
						}
					},
					"response": []
				},
				{
					"name": "Find by ID",
					"request": {
						"method": "GET",
						"header": [],
						"url": {
							"raw": "localhost:8080/profissionais/7db309e6-dab8-46d8-a14c-791e373286d3",
							"host": [
								"localhost"
							],
							"port": "8080",
							"path": [
								"profissionais",
								"7db309e6-dab8-46d8-a14c-791e373286d3"
							]
						}
					},
					"response": []
				},
				{
					"name": "Update",
					"request": {
						"method": "PUT",
						"header": [],
						"body": {
							"mode": "raw",
							"raw": "{\r\n    \"nome\": \"Fulano\",\r\n    \"cargo\": \"Desenvolvedor\",\r\n    \"nascimento\": \"1990-01-01\"\r\n}",
							"options": {
								"raw": {
									"language": "json"
								}
							}
						},
						"url": {
							"raw": "localhost:8080/profissionais/7db309e6-dab8-46d8-a14c-791e373286d3",
							"host": [
								"localhost"
							],
							"port": "8080",
							"path": [
								"profissionais",
								"7db309e6-dab8-46d8-a14c-791e373286d3"
							]
						}
					},
					"response": []
				},
				{
					"name": "Create",
					"request": {
						"method": "POST",
						"header": [],
						"body": {
							"mode": "raw",
							"raw": "{\r\n    \"nome\": \"Ciclano\",\r\n    \"cargo\": \"Designer\",\r\n    \"nascimento\": \"1990-12-01\"\r\n}",
							"options": {
								"raw": {
									"language": "json"
								}
							}
						},
						"url": {
							"raw": "localhost:8080/profissionais",
							"host": [
								"localhost"
							],
							"port": "8080",
							"path": [
								"profissionais"
							]
						}
					},
					"response": []
				},
				{
					"name": "Delete",
					"request": {
						"method": "DELETE",
						"header": [],
						"url": {
							"raw": "localhost:8080/profissionais/170d3a38-f740-4272-b26a-26e1bf92b215",
							"host": [
								"localhost"
							],
							"port": "8080",
							"path": [
								"profissionais",
								"170d3a38-f740-4272-b26a-26e1bf92b215"
							]
						}
					},
					"response": []
				}
			]
		},
		{
			"name": "Contatos",
			"item": [
				{
					"name": "List All",
					"request": {
						"method": "GET",
						"header": [],
						"url": {
							"raw": "localhost:8080/contatos",
							"host": [
								"localhost"
							],
							"port": "8080",
							"path": [
								"contatos"
							]
						}
					},
					"response": []
				},
				{
					"name": "Find by ID",
					"request": {
						"method": "GET",
						"header": [],
						"url": {
							"raw": "localhost:8080/contatos/f429b0bb-be81-4122-902e-509d45cf261d",
							"host": [
								"localhost"
							],
							"port": "8080",
							"path": [
								"contatos",
								"f429b0bb-be81-4122-902e-509d45cf261d"
							]
						}
					},
					"response": []
				},
				{
					"name": "Update",
					"request": {
						"method": "PUT",
						"header": [],
						"body": {
							"mode": "raw",
							"raw": "{\r\n    \"nome\": \"Telefone\",\r\n    \"contato\": \"00 0000-0000\"\r\n}",
							"options": {
								"raw": {
									"language": "json"
								}
							}
						},
						"url": {
							"raw": "localhost:8080/contatos/f429b0bb-be81-4122-902e-509d45cf261d",
							"host": [
								"localhost"
							],
							"port": "8080",
							"path": [
								"contatos",
								"f429b0bb-be81-4122-902e-509d45cf261d"
							]
						}
					},
					"response": []
				},
				{
					"name": "Create",
					"request": {
						"method": "POST",
						"header": [],
						"body": {
							"mode": "raw",
							"raw": "{\r\n    \"nome\": \"Telefone sem fio\",\r\n    \"contato\": \"00 00000-0000\",\r\n    \"profissionalId\": \"7db309e6-dab8-46d8-a14c-791e373286d3\"\r\n}",
							"options": {
								"raw": {
									"language": "json"
								}
							}
						},
						"url": {
							"raw": "localhost:8080/contatos",
							"host": [
								"localhost"
							],
							"port": "8080",
							"path": [
								"contatos"
							]
						}
					},
					"response": []
				},
				{
					"name": "Delete",
					"request": {
						"method": "DELETE",
						"header": [],
						"url": {
							"raw": "localhost:8080/contatos/995e1a6f-ecff-4ce4-beb1-088e73693b80",
							"host": [
								"localhost"
							],
							"port": "8080",
							"path": [
								"contatos",
								"995e1a6f-ecff-4ce4-beb1-088e73693b80"
							]
						}
					},
					"response": []
				}
			]
		}
	]
}